{
    "asset": {
        "format": "png",
        "id": "21b3465587bf8411d4938b92b7031b76",
        "name": "Screenshot(30).png",
        "path": "file:C:/Users/hadiazhar/Documents/GitHub/TrainYourOwnYOLO/Data/Source_Images/Training_images/Screenshot(30).png",
        "size": {
            "width": 1920,
            "height": 1080
        },
        "state": 2,
        "type": 1
    },
    "regions": [
        {
            "id": "IO_2E_0hZ",
            "type": "RECTANGLE",
            "tags": [
                "foreign_matter"
            ],
            "boundingBox": {
                "height": 28.8,
                "width": 67.65881267572634,
                "left": 893.6008156630741,
                "top": 455.94000549316405
            },
            "points": [
                {
                    "x": 893.6008156630741,
                    "y": 455.94000549316405
                },
                {
                    "x": 961.2596283388003,
                    "y": 455.94000549316405
                },
                {
                    "x": 961.2596283388003,
                    "y": 484.74000549316406
                },
                {
                    "x": 893.6008156630741,
                    "y": 484.74000549316406
                }
            ]
        },
        {
            "id": "uK4C8gEEb",
            "type": "RECTANGLE",
            "tags": [
                "foreign_matter"
            ],
            "boundingBox": {
                "height": 25.919989013671877,
                "width": 30.230530986410496,
                "left": 889.2821213097469,
                "top": 226.97998352050783
            },
            "points": [
                {
                    "x": 889.2821213097469,
                    "y": 226.97998352050783
                },
                {
                    "x": 919.5126522961574,
                    "y": 226.97998352050783
                },
                {
                    "x": 919.5126522961574,
                    "y": 252.89997253417968
                },
                {
                    "x": 889.2821213097469,
                    "y": 252.89997253417968
                }
            ]
        },
        {
            "id": "e9P5I-H89",
            "type": "RECTANGLE",
            "tags": [
                "foreign_matter"
            ],
            "boundingBox": {
                "height": 25.919989013671877,
                "width": 27.35147463683224,
                "left": 765.480831185567,
                "top": 261.5400054931641
            },
            "points": [
                {
                    "x": 765.480831185567,
                    "y": 261.5400054931641
                },
                {
                    "x": 792.8323058223992,
                    "y": 261.5400054931641
                },
                {
                    "x": 792.8323058223992,
                    "y": 287.4599945068359
                },
                {
                    "x": 765.480831185567,
                    "y": 287.4599945068359
                }
            ]
        },
        {
            "id": "b_NdH1Gu5",
            "type": "RECTANGLE",
            "tags": [
                "foreign_matter"
            ],
            "boundingBox": {
                "height": 21.6,
                "width": 23.032780283505154,
                "left": 729.4920776710403,
                "top": 235.6200164794922
            },
            "points": [
                {
                    "x": 729.4920776710403,
                    "y": 235.6200164794922
                },
                {
                    "x": 752.5248579545455,
                    "y": 235.6200164794922
                },
                {
                    "x": 752.5248579545455,
                    "y": 257.2200164794922
                },
                {
                    "x": 729.4920776710403,
                    "y": 257.2200164794922
                }
            ]
        },
        {
            "id": "y4AZFqIWj",
            "type": "RECTANGLE",
            "tags": [
                "foreign_matter"
            ],
            "boundingBox": {
                "height": 27.360021972656252,
                "width": 28.791002811621368,
                "left": 869.1283973758201,
                "top": 303.2999725341797
            },
            "points": [
                {
                    "x": 869.1283973758201,
                    "y": 303.2999725341797
                },
                {
                    "x": 897.9194001874414,
                    "y": 303.2999725341797
                },
                {
                    "x": 897.9194001874414,
                    "y": 330.659994506836
                },
                {
                    "x": 869.1283973758201,
                    "y": 330.659994506836
                }
            ]
        },
        {
            "id": "bdgvx_DW_",
            "type": "RECTANGLE",
            "tags": [
                "foreign_matter"
            ],
            "boundingBox": {
                "height": 20.16002197265625,
                "width": 35.98875351452671,
                "left": 1488.1349578256795,
                "top": 237.05999450683595
            },
            "points": [
                {
                    "x": 1488.1349578256795,
                    "y": 237.05999450683595
                },
                {
                    "x": 1524.1237113402062,
                    "y": 237.05999450683595
                },
                {
                    "x": 1524.1237113402062,
                    "y": 257.2200164794922
                },
                {
                    "x": 1488.1349578256795,
                    "y": 257.2200164794922
                }
            ]
        },
        {
            "id": "b_O--jtDp",
            "type": "RECTANGLE",
            "tags": [
                "foreign_matter"
            ],
            "boundingBox": {
                "height": 24.48006591796875,
                "width": 23.032780283505154,
                "left": 1204.5436240627928,
                "top": 867.7799835205078
            },
            "points": [
                {
                    "x": 1204.5436240627928,
                    "y": 867.7799835205078
                },
                {
                    "x": 1227.576404346298,
                    "y": 867.7799835205078
                },
                {
                    "x": 1227.576404346298,
                    "y": 892.2600494384766
                },
                {
                    "x": 1204.5436240627928,
                    "y": 892.2600494384766
                }
            ]
        },
        {
            "id": "tyBbLJsav",
            "type": "RECTANGLE",
            "tags": [
                "foreign_matter"
            ],
            "boundingBox": {
                "height": 33.1200439453125,
                "width": 33.10969716494845,
                "left": 1050.5116931232428,
                "top": 722.3400054931641
            },
            "points": [
                {
                    "x": 1050.5116931232428,
                    "y": 722.3400054931641
                },
                {
                    "x": 1083.6213902881912,
                    "y": 722.3400054931641
                },
                {
                    "x": 1083.6213902881912,
                    "y": 755.4600494384766
                },
                {
                    "x": 1050.5116931232428,
                    "y": 755.4600494384766
                }
            ]
        },
        {
            "id": "zw1atAfqq",
            "type": "RECTANGLE",
            "tags": [
                "foreign_matter"
            ],
            "boundingBox": {
                "height": 21.6,
                "width": 30.230530986410496,
                "left": 1429.1134240276476,
                "top": 287.4599945068359
            },
            "points": [
                {
                    "x": 1429.1134240276476,
                    "y": 287.4599945068359
                },
                {
                    "x": 1459.343955014058,
                    "y": 287.4599945068359
                },
                {
                    "x": 1459.343955014058,
                    "y": 309.05999450683595
                },
                {
                    "x": 1429.1134240276476,
                    "y": 309.05999450683595
                }
            ]
        },
        {
            "id": "NC8-qBJpz",
            "type": "RECTANGLE",
            "tags": [
                "foreign_matter"
            ],
            "boundingBox": {
                "height": 21.6,
                "width": 43.18650421743205,
                "left": 853.2933677952202,
                "top": 1024.740005493164
            },
            "points": [
                {
                    "x": 853.2933677952202,
                    "y": 1024.740005493164
                },
                {
                    "x": 896.4798720126523,
                    "y": 1024.740005493164
                },
                {
                    "x": 896.4798720126523,
                    "y": 1046.3400054931642
                },
                {
                    "x": 853.2933677952202,
                    "y": 1046.3400054931642
                }
            ]
        }
    ],
    "version": "2.2.0"
}