{
    "asset": {
        "format": "png",
        "id": "f41caa94db7a80c5ae0bd354eed31646",
        "name": "Screenshot(72).png",
        "path": "file:C:/Users/hadiazhar/Documents/GitHub/TrainYourOwnYOLO/Data/Source_Images/Training_images/Screenshot(72).png",
        "size": {
            "width": 1920,
            "height": 1080
        },
        "state": 2,
        "type": 1
    },
    "regions": [
        {
            "id": "04dYrxbdz",
            "type": "RECTANGLE",
            "tags": [
                "foreign_matter"
            ],
            "boundingBox": {
                "height": 23.03997802734375,
                "width": 20.153723933926898,
                "left": 1292.356160672446,
                "top": 261.5400054931641
            },
            "points": [
                {
                    "x": 1292.356160672446,
                    "y": 261.5400054931641
                },
                {
                    "x": 1312.509884606373,
                    "y": 261.5400054931641
                },
                {
                    "x": 1312.509884606373,
                    "y": 284.5799835205078
                },
                {
                    "x": 1292.356160672446,
                    "y": 284.5799835205078
                }
            ]
        },
        {
            "id": "tkYmqAchU",
            "type": "RECTANGLE",
            "tags": [
                "foreign_matter"
            ],
            "boundingBox": {
                "height": 24.480010986328125,
                "width": 43.18650421743205,
                "left": 1396.003726862699,
                "top": 543.7799835205078
            },
            "points": [
                {
                    "x": 1396.003726862699,
                    "y": 543.7799835205078
                },
                {
                    "x": 1439.1902310801313,
                    "y": 543.7799835205078
                },
                {
                    "x": 1439.1902310801313,
                    "y": 568.2599945068359
                },
                {
                    "x": 1396.003726862699,
                    "y": 568.2599945068359
                }
            ]
        },
        {
            "id": "yqgcPaZi2",
            "type": "RECTANGLE",
            "tags": [
                "foreign_matter"
            ],
            "boundingBox": {
                "height": 24.479956054687502,
                "width": 20.153723933926898,
                "left": 1443.5089254334582,
                "top": 792.9000274658204
            },
            "points": [
                {
                    "x": 1443.5089254334582,
                    "y": 792.9000274658204
                },
                {
                    "x": 1463.6626493673853,
                    "y": 792.9000274658204
                },
                {
                    "x": 1463.6626493673853,
                    "y": 817.3799835205078
                },
                {
                    "x": 1443.5089254334582,
                    "y": 817.3799835205078
                }
            ]
        },
        {
            "id": "A-akSqeLe",
            "type": "RECTANGLE",
            "tags": [
                "foreign_matter"
            ],
            "boundingBox": {
                "height": 20.16002197265625,
                "width": 27.35147463683224,
                "left": 276.0337284735239,
                "top": 381.05999450683595
            },
            "points": [
                {
                    "x": 276.0337284735239,
                    "y": 381.05999450683595
                },
                {
                    "x": 303.38520311035614,
                    "y": 381.05999450683595
                },
                {
                    "x": 303.38520311035614,
                    "y": 401.2200164794922
                },
                {
                    "x": 276.0337284735239,
                    "y": 401.2200164794922
                }
            ]
        },
        {
            "id": "TfV2NPet5",
            "type": "RECTANGLE",
            "tags": [
                "foreign_matter"
            ],
            "boundingBox": {
                "height": 28.8,
                "width": 15.835029580599812,
                "left": 936.7873198805061,
                "top": 281.6999725341797
            },
            "points": [
                {
                    "x": 936.7873198805061,
                    "y": 281.6999725341797
                },
                {
                    "x": 952.6223494611058,
                    "y": 281.6999725341797
                },
                {
                    "x": 952.6223494611058,
                    "y": 310.4999725341797
                },
                {
                    "x": 936.7873198805061,
                    "y": 310.4999725341797
                }
            ]
        },
        {
            "id": "L4codHCve",
            "type": "RECTANGLE",
            "tags": [
                "foreign_matter"
            ],
            "boundingBox": {
                "height": 31.6799560546875,
                "width": 25.91189154756326,
                "left": 352.3299298559044,
                "top": 922.5000274658204
            },
            "points": [
                {
                    "x": 352.3299298559044,
                    "y": 922.5000274658204
                },
                {
                    "x": 378.24182140346767,
                    "y": 922.5000274658204
                },
                {
                    "x": 378.24182140346767,
                    "y": 954.1799835205078
                },
                {
                    "x": 352.3299298559044,
                    "y": 954.1799835205078
                }
            ]
        }
    ],
    "version": "2.2.0"
}